masterkeybrute/__init__.py
masterkeybrute/masterkeybrute.py
masterkeybrute-1.1.dist-info/METADATA
masterkeybrute-1.1.dist-info/WHEEL
masterkeybrute-1.1.dist-info/entry_points.txt
masterkeybrute-1.1.dist-info/RECORD
