Metadata-Version: 2.1
Name: masterkeybrute
Version: 1.1
Summary: Bruteforce DPAPI encrypted MasterKey File from Windows Credentials Manager
Home-page: https://github.com/ProcessusT/MasterKeyBrute
License: GPL-3.0-only
Keywords: bruteforce,dpapi,windows,blob,masterkey,activedirectory,credentials
Author: Processus Thief
Author-email: processus@thiefin.fr
Maintainer: Processus Thief
Maintainer-email: processus@thiefin.fr
Requires-Python: >=3.7,<4.0
Classifier: License :: OSI Approved :: GNU General Public License v3 (GPLv3)
Classifier: Programming Language :: Python :: 3
Classifier: Programming Language :: Python :: 3.7
Classifier: Programming Language :: Python :: 3.8
Classifier: Programming Language :: Python :: 3.9
Classifier: Programming Language :: Python :: 3.10
Classifier: Programming Language :: Python :: 3.11
Classifier: Programming Language :: Python :: 3.12
Classifier: Programming Language :: Python :: 3.13
Classifier: Topic :: System :: Systems Administration :: Authentication/Directory
Classifier: Topic :: System :: Systems Administration :: Authentication/Directory :: LDAP
Requires-Dist: impacket (>=0.10.0,<0.11.0)
Requires-Dist: pycryptodomex (>=3.15.0,<4.0.0)
Project-URL: Bug Tracker, https://github.com/ProcessusT/MasterKeyBrute/issues
Project-URL: Documentation, https://github.com/ProcessusT/MasterKeyBrute
Project-URL: Repository, https://github.com/ProcessusT/MasterKeyBrute
